dsfaker/__init__.py
dsfaker/exceptions.py
dsfaker/generators/__init__.py
dsfaker/generators/autoincrement.py
dsfaker/generators/base.py
dsfaker/generators/date.py
dsfaker/generators/distributions.py
dsfaker/generators/series.py
dsfaker/generators/str.py
dsfaker/generators/timeseries.py
dsfaker/generators/trigonometric.py
dsfaker/generators/utils.py
dsfaker/noise/__init__.py
dsfaker/noise/additive_noise.py
dsfaker/noise/modulators.py
dsfaker-0.2.3.dist-info/METADATA
dsfaker-0.2.3.dist-info/RECORD
dsfaker-0.2.3.dist-info/WHEEL
dsfaker-0.2.3.dist-info/top_level.txt
