Metadata-Version: 2.1
Name: dsfaker
Version: 0.2.3
Summary: Data Science Faker
Home-page: http://github.com/dubrzr/dsfaker
Author: dubrzr
Author-email: nota@valid.addr
License: MIT
Platform: UNKNOWN
Requires-Dist: numpy (>=1.12.0)
